pencils/__init__.py
pencils/_color.py
pencils/_colors.py
pencils/_hsl.py
pencils/_palette.py
pencils/_palettes.py
pencils/_registry.py
pencils/_rgb.py
pencils/py.typed
pencils-0.1.0.dist-info/LICENSE
pencils-0.1.0.dist-info/WHEEL
pencils-0.1.0.dist-info/METADATA
pencils-0.1.0.dist-info/RECORD
