Metadata-Version: 2.1
Name: pencils
Version: 0.1.0
Summary: A collection of color palettes.
Keywords: colors,palettes,art,design,color
Author-email: Gram <gram@orsinium.dev>
Requires-Python: >=3.7
Classifier: Development Status :: 5 - Production/Stable
Classifier: Intended Audience :: Developers
Classifier: License :: OSI Approved :: MIT License
Classifier: Programming Language :: Python
Classifier: Topic :: Software Development
Requires-Dist: flake8 ; extra == "lint"
Requires-Dist: mypy ; extra == "lint"
Requires-Dist: isort ; extra == "lint"
Requires-Dist: pytest ; extra == "test"
Project-URL: Source, https://github.com/orsinium-labs/pencils
Provides-Extra: lint
Provides-Extra: test
